mozilla_repo_urls/__init__.py
mozilla_repo_urls/errors.py
mozilla_repo_urls/parser.py
mozilla_repo_urls/result.py
mozilla_repo_urls/platforms/__init__.py
mozilla_repo_urls/platforms/hgmo.py
mozilla_repo_urls-0.2.2.dist-info/METADATA
mozilla_repo_urls-0.2.2.dist-info/WHEEL
mozilla_repo_urls-0.2.2.dist-info/licenses/LICENSE
mozilla_repo_urls-0.2.2.dist-info/RECORD
