Metadata-Version: 2.4
Name: mozilla-repo-urls
Version: 0.2.2
Summary: Process Mozilla's repository URLs. The intent is to centralize URLs parsing.
Author-email: Mozilla Release Engineering <release+python@mozilla.com>
License-Expression: MPL-2.0
License-File: LICENSE
Classifier: Programming Language :: Python :: 3
Classifier: Programming Language :: Python :: 3.11
Classifier: Programming Language :: Python :: 3.12
Classifier: Programming Language :: Python :: 3.13
Requires-Python: >=3.11
Requires-Dist: giturlparse>=0.10.0
